pyEdgeworthBox/__init__.py
pyEdgeworthBox/pyEdgeworthBox.py
pyEdgeworthBox-0.3.4.dist-info/LICENSE.txt
pyEdgeworthBox-0.3.4.dist-info/METADATA
pyEdgeworthBox-0.3.4.dist-info/WHEEL
pyEdgeworthBox-0.3.4.dist-info/top_level.txt
pyEdgeworthBox-0.3.4.dist-info/RECORD
